aio_pipe.cpython-36m-x86_64-linux-gnu.so
aio_pipe-0.1.1.dist-info/WHEEL
aio_pipe-0.1.1.dist-info/top_level.txt
aio_pipe-0.1.1.dist-info/METADATA
aio_pipe-0.1.1.dist-info/metadata.json
aio_pipe-0.1.1.dist-info/DESCRIPTION.rst
aio_pipe-0.1.1.dist-info/RECORD
