Metadata-Version: 2.0
Name: aio-pipe
Version: 0.1.1
Summary: POSIX Pipe async helper
Home-page: https://github.com/mosquito/aio-pipe
Author: Dmitry Orlov
Author-email: me@mosquito.su
License: Apache 2
Keywords: posix pipe,python,asyncio,cython
Platform: POSIX
Classifier: Development Status :: 4 - Beta
Classifier: Environment :: Console
Classifier: Intended Audience :: Developers
Classifier: Intended Audience :: Education
Classifier: Intended Audience :: End Users/Desktop
Classifier: License :: OSI Approved :: Apache Software License
Classifier: Natural Language :: English
Classifier: Natural Language :: Russian
Classifier: Operating System :: POSIX :: Linux
Classifier: Operating System :: MacOS :: MacOS X
Classifier: Programming Language :: Cython
Classifier: Programming Language :: Python
Classifier: Programming Language :: Python :: 3 :: Only
Classifier: Programming Language :: Python :: 3.4
Classifier: Programming Language :: Python :: 3.5
Classifier: Programming Language :: Python :: 3.6
Classifier: Programming Language :: Python :: Implementation :: CPython
Classifier: Topic :: Software Development :: Libraries
Classifier: Topic :: System
Classifier: Topic :: System :: Operating System
